danmu.fm-0.3.6.dist-info/DESCRIPTION.rst
danmu.fm-0.3.6.dist-info/METADATA
danmu.fm-0.3.6.dist-info/RECORD
danmu.fm-0.3.6.dist-info/WHEEL
danmu.fm-0.3.6.dist-info/entry_points.txt
danmu.fm-0.3.6.dist-info/metadata.json
danmu.fm-0.3.6.dist-info/top_level.txt
danmu.fm-0.3.6.dist-info/zip-safe
danmufm/__init__.py
danmufm/cmd_config.py
danmufm/danmu.py
danmufm/settings.py
danmufm/client/__init__.py
danmufm/client/douyu_client.py
danmufm/client/douyu_danmu_manager.py
danmufm/misc/__init__.py
danmufm/misc/color_printer.py
danmufm/misc/color_stream_handler.py
danmufm/misc/downloaders.py
danmufm/misc/player.py
danmufm/model/__init__.py
danmufm/model/danmu_msg.py
danmufm/model/douyu_msg.py
danmufm/template/danmu.fm.conf
