Metadata-Version: 2.0
Name: danmu.fm
Version: 0.3.6
Summary: a tiny and smart cli player of douyu based on Python
Home-page: https://github.com/twocucao/doumu.fm
Author: twocucao
Author-email: twocucao@gmail.com
License: MIT
Keywords: python douyu danmu danmu.fm terminal
Platform: UNKNOWN
Requires-Dist: click
Requires-Dist: requests
